Workbook

Sheet README
B2: Enterprise Sales Performance & Financial Analytics Dashboard
B3: Sumerix Global — Data Analytics & Business Intelligence Internship — Task 2 Mini Project
B5: Objective
B6: Consolidate multi-region sales, cost and budget data into a single Excel analytics solution: advanced formulas, a cleaned data model, financial analysis, forecasting and an executive dashboard.
B8: Workbook Map
B9: Raw_Sales_Data
B10: Untransformed source export (246 rows) — contains the duplicates, blank Units, and inconsistent Region casing found in real exports.
B12: Cleaned_Data
B13: Result of the ETL pass: duplicates removed, blanks imputed, Region text standardized, plus calculated columns (Gross Sales, Discounts, Net Sales, COGS, Gross Profit, Margin %).
B15: Lookup_Tables
B16: Product, Region and Segment master lists, and the Monthly Budget table used for Budget-vs-Actual analysis — the equivalent of a Power Pivot data model's dimension tables.
B18: Advanced_Functions
... B40: Edit the blue/yellow input cells in Lookup_Tables (Budget) and Forecast (What-If growth %) — every dependent formula recalculates automatically.

Sheet Raw_Sales_Data
A1: Raw Sales Export (Source System) — contains duplicates, blanks, inconsistent casing
A3: Ref No | B3: Date | C3: Region | D3: Product | E3: Category | F3: Segment | G3: Units Sold | H3: Manufacturing Price | I3: Sale Price | J3: Discount %
A4: TXN-1098 | B4: 2025-05-06 | C4: South America | D4: Product C | E4: Home & Living | F4: Online | G4: 126 | H4: 21.85 | I4: 44.94 | J4: 0.1
A5: TXN-1108 | B5: 2025-06-23 | C5: Europe | D5: Product C | E5: Home & Living | F5: Wholesale | G5: 171 | H5: 21.75 | I5: 42.87 | J5: 0.1
A6: TXN-1161 | B6: 2025-09-08 | C6: north america | D6: Product A | E6: Electronics | F6: Wholesale | G6: 213 | H6: 70.83 | I6: 116.26 | J6: 0.15
A7: TXN-1042 | B7: 2025-03-10 | C7: North America | D7: Product B | E7: Electronics | F7: Wholesale | G7: 201 | H7: 51.46 | I7: 83.97 | J7: 0.05
A8: TXN-1008 | B8: 2025-01-07 | C8: Europe | D8: Product C | E8: Home & Living | F8: Online | G8: 207 | H8: 22.16 | I8: 46.48 | J8: 0.05
A9: TXN-1132 | B9: 2025-07-26 | C9: Asia | D9: Product B | E9: Electronics | F9: Online | G9: 174 | H9: 50.79 | I9: 81.76 | J9: 0.15
A10: TXN-1146 | B10: 2025-08-12 | C10: Europe | D10: Product A | E10: Electronics | F10: Wholesale | G10: 202 | H10: 71.32 | I10: 119.23 | J10: 0
A11: TXN-1173 | B11: 2025-09-08 | C11: Asia | D11: Product C | E11: Home & Living | F11: Online | G11: 224 | H11: 22.49 | I11: 43.11 | J11: 0.15
A12: TXN-1196 | B12: 2025-10-02 | C12: South America | D12: Product A | E12: Electronics | F12: Wholesale | G12: 177 | H12: 69.96 | I12: 115.19 | J12: 0.1
A13: TXN-1013 | B13: 2025-01-08 | C13: Asia | D13: Product C | E13: Home & Living | F13: Retail | G13: 164 | H13: 21.63 | I13: 45.85 | J13: 0.05
A14: TXN-1035 | B14: 2025-02-14 | C14: Asia | D14: Product E | E14: Apparel | F14: Wholesale | G14: 197 | H14: 27.32 | I14: 58.14 | J14: 0.1
A15: TXN-1012 | B15: 2025-01-13 | C15: Asia | D15: Product B | E15: Electronics | F15: Wholesale | G15: 222 | H15: 50.69 | I15: 82.2 | J15: 0
... A20: TXN-1175 | B20: 2025-09-18 | C20: Asia | D20: Product E | E20: Apparel | F20: Online | G20: 216 | H20: 28.51 | I20: 57.06 | J20: 0.05
A21: TXN-1038 | B21: 2025-02-09 | C21: South America | D21: Product C | E21: Home & Living | F21: Retail | H21: 21.93 | I21: 43.61 | J21: 0.1
A22: TXN-1046 | B22: 2025-03-20 | C22: europe | D22: Product A | E22: Electronics | F22: Retail | G22: 220 | H22: 68.24 | I22: 125.53 | J22: 0
A23: TXN-1001 | B23: 2025-01-24 | C23: North America | D23: Product A | E23: Electronics | F23: Online | G23: 206 | H23: 68.84 | I23: 117.3 | J23: 0
A24: TXN-1111 | B24: 2025-06-27 | C24: Asia | D24: Product A | E24: Electronics | F24: Wholesale | G24: 137 | H24: 70.62 | I24: 114.83 | J24: 0
A25: TXN-1215 | B25: 2025-11-09 | C25: Asia | D25: Product E | E25: Apparel | F25: Online | G25: 279 | H25: 27.69 | I25: 61.38 | J25: 0.05
A26: TXN-1052 | B26: 2025-03-03 | C26: Asia | D26: Product B | E26: Electronics | F26: Wholesale | G26: 144 | H26: 50.02 | I26: 85.32 | J26: 0
A27: TXN-1137 | B27: 2025-07-22 | C27: South America | D27: Product B | E27: Electronics | F27: Retail | G27: 156 | H27: 50.62 | I27: 82.72 | J27: 0.1
A28: TXN-1043 | B28: 2025-03-07 | C28: North America | D28: Product C | E28: Home & Living | F28: Retail | G28: 114 | H28: 22.07 | I28: 47.23 | J28: 0.1
A29: TXN-1120 | B29: 2025-06-03 | C29: South America | D29: Product E | E29: Apparel | F29: Retail | G29: 177 | H29: 28.36 | I29: 59.86 | J29: 0.1
A30: TXN-1136 | B30: 2025-07-23 | C30: South America | D30: Product A | E30: Electronics | F30: Wholesale | G30: 176 | H30: 68.56 | I30: 120.62 | J30: 0.1
A31: TXN-1051 | B31: 2025-03-03 | C31: Asia | D31: Product A | E31: Electronics | F31: Retail | H31: 70.51 | I31: 114.11 | J31: 0.15
A32: TXN-1118 | B32: 2025-06-01 | C32: South America | D32: Product C | E32: Home & Living | F32: Online | G32: 220 | H32: 22.13 | I32: 44.01 | J32: 0.05
A33: TXN-1063 | B33: 2025-04-24 | C33: North America | D33: Product C | E33: Home & Living | F33: Online | G33: 231 | H33: 22.51 | I33: 46.26 | J33: 0.1
A34: TXN-1184 | B34: 2025-10-14 | C34: North America | D34: Product D | E34: Apparel | F34: Online | G34: 219 | H34: 14.34 | I34: 28.89 | J34: 0.05
A35: TXN-1234 | B35: 2025-12-13 | C35: Asia | D35: Product D | E35: Apparel | F35: Retail | G35: 304 | H35: 14.28 | I35: 30 | J35: 0.05
A36: TXN-1003 | B36: 2025-01-08 | C36: North America | D36: Product C | E36: Home & Living | F36: Wholesale | G36: 241 | H36: 22.08 | I36: 45.46 | J36: 0.15
A37: TXN-1009 | B37: 2025-01-28 | C37: Europe | D37: Product D | E37: Apparel | F37: Retail | G37: 190 | H37: 13.82 | I37: 29.18 | J37: 0
A38: TXN-1082 | B38: 2025-05-08 | C38: North America | D38: Product B | E38: Electronics | F38: Retail | G38: 314 | H38: 49.1 | I38: 82.66 | J38: 0
A39: TXN-1103 | B39: 2025-06-21 | C39: North America | D39: Product C | E39: Home & Living | F39: Retail | G39: 253 | H39: 22.66 | I39: 45.18 | J39: 0.05
A40: TXN-1239 | B40: 2025-12-25 | C40: South America | D40: Product D | E40: Apparel | F40: Wholesale | G40: 214 | H40: 14.21 | I40: 31.11 | J40: 0
A41: TXN-1075 | B41: 2025-04-13 | C41: Asia | D41: Product E | E41: Apparel | F41: Wholesale | G41: 180 | H41: 28.01 | I41: 62.4 | J41: 0.1
A42: TXN-1185 | B42: 2025-10-09 | C42: North America | D42: Product E | E42: Apparel | F42: Online | G42: 283 | H42: 28.79 | I42: 60.24 | J42: 0.15
A43: TXN-1106 | B43: 2025-06-20 | C43: Europe | D43: Product A | E43: Electronics | F43: Retail | G43: 232 | H43: 68.98 | I43: 119.58 | J43: 0.05
... A46: TXN-1216 | B46: 2025-11-03 | C46: South America | D46: Product A | E46: Electronics | F46: Retail | G46: 181 | H46: 68.54 | I46: 118.49 | J46: 0.1
A47: TXN-1066 | B47: 2025-04-08 | C47: Europe | D47: Product A | E47: Electronics | F47: Wholesale | H47: 68.35 | I47: 123.45 | J47: 0
A48: TXN-1159 | B48: 2025-08-15 | C48: South America | D48: Product D | E48: Apparel | F48: Retail | G48: 257 | H48: 14.07 | I48: 31.01 | J48: 0.1
A49: TXN-1059 | B49: 2025-03-01 | C49: South America | D49: Product D | E49: Apparel | F49: Online | G49: 237 | H49: 13.95 | I49: 28.98 | J49: 0.1
A50: TXN-1205 | B50: 2025-11-05 | C50: North America | D50: Product E | E50: Apparel | F50: Retail | G50: 230 | H50: 27.19 | I50: 60.53 | J50: 0.05
A51: TXN-1004 | B51: 2025-01-23 | C51: North America | D51: Product D | E51: Apparel | F51: Retail | G51: 232 | H51: 13.81 | I51: 29.85 | J51: 0
A52: TXN-1198 | B52: 2025-10-13 | C52: SOUTH AMERICA | D52: Product C | E52: Home & Living | F52: Retail | G52: 170 | H52: 22.53 | I52: 44.4 | J52: 0.05
A53: TXN-1002 | B53: 2025-01-01 | C53: North America | D53: Product B | E53: Electronics | F53: Retail | G53: 205 | H53: 48.76 | I53: 88.33 | J53: 0.1
A54: TXN-1023 | B54: 2025-02-07 | C54: North America | D54: Product C | E54: Home & Living | F54: Online | G54: 266 | H54: 21.73 | I54: 46.67 | J54: 0.15
A55: TXN-1081 | B55: 2025-05-10 | C55: North America | D55: Product A | E55: Electronics | F55: Online | G55: 221 | H55: 68.29 | I55: 121.43 | J55: 0
A56: TXN-1229 | B56: 2025-12-12 | C56: Europe | D56: Product D | E56: Apparel | F56: Retail | G56: 246 | H56: 13.81 | I56: 29.83 | J56: 0.15
A57: TXN-1179 | B57: 2025-09-01 | C57: South America | D57: Product D | E57: Apparel | F57: Wholesale | G57: 175 | H57: 14.28 | I57: 28.57 | J57: 0.1
A58: TXN-1028 | B58: 2025-02-14 | C58: Europe | D58: Product C | E58: Home & Living | F58: Online | G58: 201 | H58: 21.56 | I58: 47.01 | J58: 0.15
A59: TXN-1202 | B59: 2025-11-26 | C59: North America | D59: Product B | E59: Electronics | F59: Retail | G59: 483 | H59: 51.11 | I59: 82.59 | J59: 0.05
... A74: TXN-1007 | B74: 2025-01-10 | C74: Europe | D74: Product B | E74: Electronics | F74: Online | G74: 240 | H74: 51.27 | I74: 81.81 | J74: 0
A75: TXN-1209 | B75: 2025-11-04 | C75: Europe | D75: Product D | E75: Apparel | F75: Online | H75: 14.29 | I75: 31.5 | J75: 0.1
A76: TXN-1187 | B76: 2025-10-24 | C76: Europe | D76: Product B | E76: Electronics | F76: Online | G76: 313 | H76: 48.73 | I76: 84.73 | J76: 0
A77: TXN-1128 | B77: 2025-07-28 | C77: Europe | D77: Product C | E77: Home & Living | F77: Retail | G77: 234 | H77: 22.18 | I77: 47 | J77: 0.1
A78: TXN-1110 | B78: 2025-06-12 | C78: Europe | D78: Product E | E78: Apparel | F78: Retail | G78: 285 | H78: 28.5 | I78: 61.83 | J78: 0.15
A79: TXN-1054 | B79: 2025-03-22 | C79: Asia | D79: Product D | E79: Apparel | F79: Wholesale | G79: 159 | H79: 13.59 | I79: 30.46 | J79: 0.15
A80: TXN-1090 | B80: 2025-05-09 | C80: europe | D80: Product E | E80: Apparel | F80: Online | G80: 161 | H80: 27.6 | I80: 59.85 | J80: 0
A81: TXN-1127 | B81: 2025-07-23 | C81: EUROPE | D81: Product B | E81: Electronics | F81: Wholesale | G81: 291 | H81: 51.42 | I81: 83.08 | J81: 0.15
A82: TXN-1112 | B82: 2025-06-27 | C82: Asia | D82: Product B | E82: Electronics | F82: Online | G82: 188 | H82: 49.8 | I82: 84.92 | J82: 0.05
A83: TXN-1092 | B83: 2025-05-05 | C83: Asia | D83: Product B | E83: Electronics | F83: Retail | G83: 143 | H83: 49.51 | I83: 82.74 | J83: 0.15
A84: TXN-1060 | B84: 2025-03-02 | C84: South America | D84: Product E | E84: Apparel | F84: Online | G84: 242 | H84: 28.75 | I84: 57.67 | J84: 0
A85: TXN-1189 | B85: 2025-10-13 | C85: Europe | D85: Product D | E85: Apparel | F85: Online | G85: 248 | H85: 13.96 | I85: 30.11 | J85: 0.05
A86: TXN-1226 | B86: 2025-12-06 | C86: Europe | D86: Product A | E86: Electronics | F86: Wholesale | G86: 317 | H86: 69.48 | I86: 120.37 | J86: 0.1
A87: TXN-1048 | B87: 2025-03-19 | C87: Europe | D87: Product C | E87: Home & Living | F87: Online | G87: 243 | H87: 22.16 | I87: 45.43 | J87: 0.1
A88: TXN-1168 | B88: 2025-09-02 | C88: europe | D88: Product C | E88: Home & Living | F88: Online | G88: 202 | H88: 22.51 | I88: 45.57 | J88: 0.1
A89: TXN-1061 | B89: 2025-04-26 | C89: North America | D89: Product A | E89: Electronics | F89: Wholesale | H89: 68.44 | I89: 115.78 | J89: 0.05
A90: TXN-1207 | B90: 2025-11-24 | C90: Europe | D90: Product B | E90: Electronics | F90: Retail | G90: 292 | H90: 50.01 | I90: 81.68 | J90: 0.15
A91: TXN-1123 | B91: 2025-07-04 | C91: North America | D91: Product C | E91: Home & Living | F91: Wholesale | G91: 237 | H91: 21.5 | I91: 43.88 | J91: 0
A92: TXN-1069 | B92: 2025-04-01 | C92: Europe | D92: Product D | E92: Apparel | F92: Wholesale | G92: 199 | H92: 14.4 | I92: 29.7 | J92: 0.15
A93: TXN-1030 | B93: 2025-02-04 | C93: Europe | D93: Product E | E93: Apparel | F93: Wholesale | G93: 177 | H93: 27.9 | I93: 60.9 | J93: 0.15
A94: TXN-1133 | B94: 2025-07-14 | C94: Asia | D94: Product C | E94: Home & Living | F94: Online | G94: 148 | H94: 22.54 | I94: 44.46 | J94: 0.05
A95: TXN-1220 | B95: 2025-11-05 | C95: South America | D95: Product E | E95: Apparel | F95: Retail | G95: 280 | H95: 27.33 | I95: 58.87 | J95: 0.15
A96: TXN-1079 | B96: 2025-04-16 | C96: South America | D96: Product D | E96: Apparel | F96: Online | G96: 122 | H96: 13.95 | I96: 29.89 | J96: 0
A97: TXN-1163 | B97: 2025-09-02 | C97: North America | D97: Product C | E97: Home & Living | F97: Wholesale | G97: 233 | H97: 22.22 | I97: 44.49 | J97: 0
A98: TXN-1031 | B98: 2025-02-01 | C98: Asia | D98: Product A | E98: Electronics | F98: Retail | G98: 181 | H98: 70.23 | I98: 114.25 | J98: 0.15
A99: TXN-1102 | B99: 2025-06-27 | C99: North America | D99: Product B | E99: Electronics | F99: Wholesale | G99: 248 | H99: 49.33 | I99: 88.23 | J99: 0.1
A100: TXN-1177 | B100: 2025-09-28 | C100: South America | D100: Product B | E100: Electronics | F100: Wholesale | G100: 165 | H100: 51.04 | I100: 82.88 | J100: 0
A101: TXN-1138 | B101: 2025-07-26 | C101: South America | D101: Product C | E101: Home & Living | F101: Online | G101: 166 | H101: 21.69 | I101: 43.8 | J101: 0.15
... A194: TXN-1211 | B194: 2025-11-11 | C194: Asia | D194: Product A | E194: Electronics | F194: Online | G194: 236 | H194: 70.56 | I194: 117.3 | J194: 0.15
A195: TXN-1045 | B195: 2025-03-02 | C195: North America | D195: Product E | E195: Apparel | F195: Retail | H195: 27.96 | I195: 57.3 | J195: 0.15
A196: TXN-1224 | B196: 2025-12-01 | C196: North America | D196: Product D | E196: Apparel | F196: Wholesale | G196: 225 | H196: 14.22 | I196: 29.32 | J196: 0.05
A197: TXN-1218 | B197: 2025-11-04 | C197: South America | D197: Product C | E197: Home & Living | F197: Online | G197: 207 | H197: 22.08 | I197: 45.39 | J197: 0.05
A198: TXN-1022 | B198: 2025-02-25 | C198: North America | D198: Product B | E198: Electronics | F198: Online | G198: 286 | H198: 49.86 | I198: 84.45 | J198: 0.05
A199: TXN-1183 | B199: 2025-10-24 | C199: North America | D199: Product C | E199: Home & Living | F199: Wholesale | G199: 339 | H199: 21.92 | I199: 44.14 | J199: 0.15
A200: TXN-1088 | B200: 2025-05-27 | C200: Europe | D200: Product C | E200: Home & Living | F200: Online | G200: 311 | H200: 22.34 | I200: 44.18 | J200: 0.1
A201: TXN-1027 | B201: 2025-02-16 | C201: Europe | D201: Product B | E201: Electronics | F201: Online | H201: 50.8 | I201: 87.22 | J201: 0
A202: TXN-1210 | B202: 2025-11-11 | C202: Europe | D202: Product E | E202: Apparel | F202: Retail | G202: 267 | H202: 28.69 | I202: 59.94 | J202: 0
A203: TXN-1016 | B203: 2025-01-18 | C203: South America | D203: Product A | E203: Electronics | F203: Online | G203: 238 | H203: 69.01 | I203: 119.51 | J203: 0
A204: TXN-1039 | B204: 2025-02-02 | C204: South America | D204: Product D | E204: Apparel | F204: Retail | G204: 90 | H204: 14.26 | I204: 28.73 | J204: 0.15
A205: TXN-1129 | B205: 2025-07-28 | C205: Europe | D205: Product D | E205: Apparel | F205: Wholesale | G205: 270 | H205: 13.87 | I205: 29.94 | J205: 0
A206: TXN-1122 | B206: 2025-07-12 | C206: North America | D206: Product B | E206: Electronics | F206: Wholesale | G206: 304 | H206: 49.78 | I206: 85.26 | J206: 0.15
A207: TXN-1155 | B207: 2025-08-27 | C207: ASIA | D207: Product E | E207: Apparel | F207: Wholesale | G207: 195 | H207: 27.65 | I207: 62.6 | J207: 0.05
A208: TXN-1083 | B208: 2025-05-23 | C208: North America | D208: Product C | E208: Home & Living | F208: Retail | G208: 310 | H208: 21.94 | I208: 46.21 | J208: 0.15
A209: TXN-1049 | B209: 2025-03-09 | C209: Europe | D209: Product D | E209: Apparel | F209: Retail | G209: 169 | H209: 14.14 | I209: 29.28 | J209: 0.05
A210: TXN-1167 | B210: 2025-09-11 | C210: Europe | D210: Product B | E210: Electronics | F210: Wholesale | G210: 201 | H210: 49.49 | I210: 81.43 | J210: 0.15
A211: TXN-1147 | B211: 2025-08-16 | C211: Europe | D211: Product B | E211: Electronics | F211: Online | G211: 195 | H211: 48.98 | I211: 81.64 | J211: 0.1
A212: TXN-1208 | B212: 2025-11-15 | C212: Europe | D212: Product C | E212: Home & Living | F212: Wholesale | G212: 206 | H212: 22.48 | I212: 46.27 | J212: 0.15
A213: TXN-1231 | B213: 2025-12-10 | C213: Asia | D213: Product A | E213: Electronics | F213: Retail | G213: 249 | H213: 70.42 | I213: 118.74 | J213: 0
...

Sheet Cleaned_Data
A1: Cleaned & Transformed Data (ETL output) — duplicates removed, blanks imputed, calculated columns added
A3: Ref No | B3: Date | C3: Month | D3: Region | E3: Product | F3: Category | G3: Segment | H3: Units Sold | I3: Manuf. Price | J3: Sale Price | K3: Discount % | L3: Gross Sales | M3: Discount Amt | N3: Net Sales | O3: COGS | P3: Gross Profit | Q3: Margin %
A4: TXN-1002 | B4: 2025-01-01 | C4: =TEXT(B4,"mmm-yyyy") -> Jan-2025 | D4: North America | E4: Product B | F4: Electronics | G4: Retail | H4: 205 | I4: 48.76 | J4: 88.33 | K4: 0.1 | L4: =H4*J4 -> 18107.65 | M4: =L4*K4 -> 1810.765 | N4: =L4-M4 -> 16296.885 | O4: =H4*I4 -> 9995.8 | P4: =N4-O4 -> 6301.085 | Q4: =IFERROR(P4/N4,0) -> 0.38664352
A5: TXN-1014 | B5: 2025-01-03 | C5: =TEXT(B5,"mmm-yyyy") -> Jan-2025 | D5: Asia | E5: Product D | F5: Apparel | G5: Wholesale | H5: 264 | I5: 14.26 | J5: 30.97 | K5: 0.1 | L5: =H5*J5 -> 8176.08 | M5: =L5*K5 -> 817.608 | N5: =L5-M5 -> 7358.472 | O5: =H5*I5 -> 3764.64 | P5: =N5-O5 -> 3593.832 | Q5: =IFERROR(P5/N5,0) -> 0.48839379
A6: TXN-1017 | B6: 2025-01-05 | C6: =TEXT(B6,"mmm-yyyy") -> Jan-2025 | D6: South America | E6: Product B | F6: Electronics | G6: Retail | H6: 101 | I6: 50.25 | J6: 84.39 | K6: 0.05 | L6: =H6*J6 -> 8523.39 | M6: =L6*K6 -> 426.1695 | N6: =L6-M6 -> 8097.2205 | O6: =H6*I6 -> 5075.25 | P6: =N6-O6 -> 3021.9705 | Q6: =IFERROR(P6/N6,0) -> 0.37321084
A7: TXN-1018 | B7: 2025-01-05 | C7: =TEXT(B7,"mmm-yyyy") -> Jan-2025 | D7: South America | E7: Product C | F7: Home & Living | G7: Retail | H7: 143 | I7: 21.46 | J7: 45.04 | K7: 0 | L7: =H7*J7 -> 6440.72 | M7: =L7*K7 -> 0 | N7: =L7-M7 -> 6440.72 | O7: =H7*I7 -> 3068.78 | P7: =N7-O7 -> 3371.94 | Q7: =IFERROR(P7/N7,0) -> 0.52353464
A8: TXN-1008 | B8: 2025-01-07 | C8: =TEXT(B8,"mmm-yyyy") -> Jan-2025 | D8: Europe | E8: Product C | F8: Home & Living | G8: Online | H8: 207 | I8: 22.16 | J8: 46.48 | K8: 0.05 | L8: =H8*J8 -> 9621.36 | M8: =L8*K8 -> 481.068 | N8: =L8-M8 -> 9140.292 | O8: =H8*I8 -> 4587.12 | P8: =N8-O8 -> 4553.172 | Q8: =IFERROR(P8/N8,0) -> 0.49814295
A9: TXN-1013 | B9: 2025-01-08 | C9: =TEXT(B9,"mmm-yyyy") -> Jan-2025 | D9: Asia | E9: Product C | F9: Home & Living | G9: Retail | H9: 164 | I9: 21.63 | J9: 45.85 | K9: 0.05 | L9: =H9*J9 -> 7519.4 | M9: =L9*K9 -> 375.97 | N9: =L9-M9 -> 7143.43 | O9: =H9*I9 -> 3547.32 | P9: =N9-O9 -> 3596.11 | Q9: =IFERROR(P9/N9,0) -> 0.50341503
A10: TXN-1003 | B10: 2025-01-08 | C10: =TEXT(B10,"mmm-yyyy") -> Jan-2025 | D10: North America | E10: Product C | F10: Home & Living | G10: Wholesale | H10: 241 | I10: 22.08 | J10: 45.46 | K10: 0.15 | L10: =H10*J10 -> 10955.86 | M10: =L10*K10 -> 1643.379 | N10: =L10-M10 -> 9312.481 | O10: =H10*I10 -> 5321.28 | P10: =N10-O10 -> 3991.201 | Q10: =IFERROR(P10/N10,0) -> 0.42858622
A11: TXN-1007 | B11: 2025-01-10 | C11: =TEXT(B11,"mmm-yyyy") -> Jan-2025 | D11: Europe | E11: Product B | F11: Electronics | G11: Online | H11: 240 | I11: 51.27 | J11: 81.81 | K11: 0 | L11: =H11*J11 -> 19634.4 | M11: =L11*K11 -> 0 | N11: =L11-M11 -> 19634.4 | O11: =H11*I11 -> 12304.8 | P11: =N11-O11 -> 7329.6 | Q11: =IFERROR(P11/N11,0) -> 0.373304
A12: TXN-1010 | B12: 2025-01-12 | C12: =TEXT(B12,"mmm-yyyy") -> Jan-2025 | D12: Europe | E12: Product E | F12: Apparel | G12: Retail | H12: 181 | I12: 27.63 | J12: 57.61 | K12: 0.05 | L12: =H12*J12 -> 10427.41 | M12: =L12*K12 -> 521.3705 | N12: =L12-M12 -> 9906.0395 | O12: =H12*I12 -> 5001.03 | P12: =N12-O12 -> 4905.0095 | Q12: =IFERROR(P12/N12,0) -> 0.49515344
A13: TXN-1012 | B13: 2025-01-13 | C13: =TEXT(B13,"mmm-yyyy") -> Jan-2025 | D13: Asia | E13: Product B | F13: Electronics | G13: Wholesale | H13: 222 | I13: 50.69 | J13: 82.2 | K13: 0 | L13: =H13*J13 -> 18248.4 | M13: =L13*K13 -> 0 | N13: =L13-M13 -> 18248.4 | O13: =H13*I13 -> 11253.18 | P13: =N13-O13 -> 6995.22 | Q13: =IFERROR(P13/N13,0) -> 0.38333333
A14: TXN-1005 | B14: 2025-01-13 | C14: =TEXT(B14,"mmm-yyyy") -> Jan-2025 | D14: North America | E14: Product E | F14: Apparel | G14: Retail | H14: 179 | I14: 28.44 | J14: 58.29 | K14: 0 | L14: =H14*J14 -> 10433.91 | M14: =L14*K14 -> 0 | N14: =L14-M14 -> 10433.91 | O14: =H14*I14 -> 5090.76 | P14: =N14-O14 -> 5343.15 | Q14: =IFERROR(P14/N14,0) -> 0.5120947
A15: TXN-1019 | B15: 2025-01-15 | C15: =TEXT(B15,"mmm-yyyy") -> Jan-2025 | D15: South America | E15: Product D | F15: Apparel | G15: Online | H15: 114 | I15: 13.63 | J15: 29.77 | K15: 0.1 | L15: =H15*J15 -> 3393.78 | M15: =L15*K15 -> 339.378 | N15: =L15-M15 -> 3054.402 | O15: =H15*I15 -> 1553.82 | P15: =N15-O15 -> 1500.582 | Q15: =IFERROR(P15/N15,0) -> 0.49128504
... A243: TXN-1239 | B243: 2025-12-25 | C243: =TEXT(B243,"mmm-yyyy") -> Dec-2025 | D243: South America | E243: Product D | F243: Apparel | G243: Wholesale | H243: 214 | I243: 14.21 | J243: 31.11 | K243: 0 | L243: =H243*J243 -> 6657.54 | M243: =L243*K243 -> 0 | N243: =L243-M243 -> 6657.54 | O243: =H243*I243 -> 3040.94 | P243: =N243-O243 -> 3616.6 | Q243: =IFERROR(P243/N243,0) -> 0.54323369

Sheet Lookup_Tables
A1: Data Model — Dimension Tables & Monthly Budget (Power Pivot equivalent)
A3: Product Master | H3: Monthly Budget (Input — edit blue/yellow cells)
A4: Product | B4: Category | C4: Target Margin % | H4: Month | I4: Region | J4: Budget Revenue | K4: Budget Expense | L4: Actual Revenue (link) | M4: Actual Expense (link)
A5: Product A | B5: Electronics | C5: 0.35 | H5: Jan-2025 | I5: North America | J5: 66770 | K5: 45420 | L5: =SUMIFS(Cleaned_Data!$N$4:$N$243,Cleaned_Data!$C$4:$C$243,$H5,Cleaned_Data!$D$4:$D$243,$I5) -> 67132.276 | M5: =SUMIFS(Cleaned_Data!$O$4:$O$243,Cleaned_Data!$C$4:$C$243,$H5,Cleaned_Data!$D$4:$D$243,$I5)+L5*0.18 -> 49876.61
A6: Product B | B6: Electronics | C6: 0.35 | H6: Jan-2025 | I6: Europe | J6: 68640 | K6: 51650 | L6: =SUMIFS(Cleaned_Data!$N$4:$N$243,Cleaned_Data!$C$4:$C$243,$H6,Cleaned_Data!$D$4:$D$243,$I6) -> 64780.991 | M6: =SUMIFS(Cleaned_Data!$O$4:$O$243,Cleaned_Data!$C$4:$C$243,$H6,Cleaned_Data!$D$4:$D$243,$I6)+L6*0.18 -> 51185.928
A7: Product C | B7: Home & Living | C7: 0.4 | H7: Jan-2025 | I7: Asia | J7: 59100 | K7: 40620 | L7: =SUMIFS(Cleaned_Data!$N$4:$N$243,Cleaned_Data!$C$4:$C$243,$H7,Cleaned_Data!$D$4:$D$243,$I7) -> 60983.834 | M7: =SUMIFS(Cleaned_Data!$O$4:$O$243,Cleaned_Data!$C$4:$C$243,$H7,Cleaned_Data!$D$4:$D$243,$I7)+L7*0.18 -> 44932.65
A8: Product D | B8: Apparel | C8: 0.45 | H8: Jan-2025 | I8: South America | J8: 54190 | K8: 38300 | L8: =SUMIFS(Cleaned_Data!$N$4:$N$243,Cleaned_Data!$C$4:$C$243,$H8,Cleaned_Data!$D$4:$D$243,$I8) -> 52834.933 | M8: =SUMIFS(Cleaned_Data!$O$4:$O$243,Cleaned_Data!$C$4:$C$243,$H8,Cleaned_Data!$D$4:$D$243,$I8)+L8*0.18 -> 38885.788
A9: Product E | B9: Apparel | C9: 0.4 | H9: Feb-2025 | I9: North America | J9: 86360 | K9: 65870 | L9: =SUMIFS(Cleaned_Data!$N$4:$N$243,Cleaned_Data!$C$4:$C$243,$H9,Cleaned_Data!$D$4:$D$243,$I9) -> 85227.425 | M9: =SUMIFS(Cleaned_Data!$O$4:$O$243,Cleaned_Data!$C$4:$C$243,$H9,Cleaned_Data!$D$4:$D$243,$I9)+L9*0.18 -> 65662.156
H10: Feb-2025 | I10: Europe | J10: 63040 | K10: 48180 | L10: =SUMIFS(Cleaned_Data!$N$4:$N$243,Cleaned_Data!$C$4:$C$243,$H10,Cleaned_Data!$D$4:$D$243,$I10) -> 66854.833 | M10: =SUMIFS(Cleaned_Data!$O$4:$O$243,Cleaned_Data!$C$4:$C$243,$H10,Cleaned_Data!$D$4:$D$243,$I10)+L10*0.18 -> 49744.13
H11: Feb-2025 | I11: Asia | J11: 52830 | K11: 40700 | L11: =SUMIFS(Cleaned_Data!$N$4:$N$243,Cleaned_Data!$C$4:$C$243,$H11,Cleaned_Data!$D$4:$D$243,$I11) -> 56524.2 | M11: =SUMIFS(Cleaned_Data!$O$4:$O$243,Cleaned_Data!$C$4:$C$243,$H11,Cleaned_Data!$D$4:$D$243,$I11)+L11*0.18 -> 44758.176
A12: Region Master | H12: Feb-2025 | I12: South America | J12: 48150 | K12: 35940 | L12: =SUMIFS(Cleaned_Data!$N$4:$N$243,Cleaned_Data!$C$4:$C$243,$H12,Cleaned_Data!$D$4:$D$243,$I12) -> 47038.449 | M12: =SUMIFS(Cleaned_Data!$O$4:$O$243,Cleaned_Data!$C$4:$C$243,$H12,Cleaned_Data!$D$4:$D$243,$I12)+L12*0.18 -> 34678.331
A13: Region | B13: Regional Manager | H13: Mar-2025 | I13: North America | J13: 65800 | K13: 49020 | L13: =SUMIFS(Cleaned_Data!$N$4:$N$243,Cleaned_Data!$C$4:$C$243,$H13,Cleaned_Data!$D$4:$D$243,$I13) -> 66260.277 | M13: =SUMIFS(Cleaned_Data!$O$4:$O$243,Cleaned_Data!$C$4:$C$243,$H13,Cleaned_Data!$D$4:$D$243,$I13)+L13*0.18 -> 52525.53
A14: North America | B14: J. Alvarez | H14: Mar-2025 | I14: Europe | J14: 76760 | K14: 57580 | L14: =SUMIFS(Cleaned_Data!$N$4:$N$243,Cleaned_Data!$C$4:$C$243,$H14,Cleaned_Data!$D$4:$D$243,$I14) -> 73576.594 | M14: =SUMIFS(Cleaned_Data!$O$4:$O$243,Cleaned_Data!$C$4:$C$243,$H14,Cleaned_Data!$D$4:$D$243,$I14)+L14*0.18 -> 56186.387
A15: Europe | B15: S. Novak | H15: Mar-2025 | I15: Asia | J15: 54600 | K15: 43610 | L15: =SUMIFS(Cleaned_Data!$N$4:$N$243,Cleaned_Data!$C$4:$C$243,$H15,Cleaned_Data!$D$4:$D$243,$I15) -> 55823.031 | M15: =SUMIFS(Cleaned_Data!$O$4:$O$243,Cleaned_Data!$C$4:$C$243,$H15,Cleaned_Data!$D$4:$D$243,$I15)+L15*0.18 -> 44529.236
A16: Asia | B16: R. Tan | H16: Mar-2025 | I16: South America | J16: 64370 | K16: 43420 | L16: =SUMIFS(Cleaned_Data!$N$4:$N$243,Cleaned_Data!$C$4:$C$243,$H16,Cleaned_Data!$D$4:$D$243,$I16) -> 62733.906 | M16: =SUMIFS(Cleaned_Data!$O$4:$O$243,Cleaned_Data!$C$4:$C$243,$H16,Cleaned_Data!$D$4:$D$243,$I16)+L16*0.18 -> 46814.403
A17: South America | B17: M. Duarte | H17: Apr-2025 | I17: North America | J17: 67760 | K17: 52160 | L17: =SUMIFS(Cleaned_Data!$N$4:$N$243,Cleaned_Data!$C$4:$C$243,$H17,Cleaned_Data!$D$4:$D$243,$I17) -> 74901.883 | M17: =SUMIFS(Cleaned_Data!$O$4:$O$243,Cleaned_Data!$C$4:$C$243,$H17,Cleaned_Data!$D$4:$D$243,$I17)+L17*0.18 -> 55172.289
H18: Apr-2025 | I18: Europe | J18: 73590 | K18: 59290 | L18: =SUMIFS(Cleaned_Data!$N$4:$N$243,Cleaned_Data!$C$4:$C$243,$H18,Cleaned_Data!$D$4:$D$243,$I18) -> 83333.039 | M18: =SUMIFS(Cleaned_Data!$O$4:$O$243,Cleaned_Data!$C$4:$C$243,$H18,Cleaned_Data!$D$4:$D$243,$I18)+L18*0.18 -> 60796.687
H19: Apr-2025 | I19: Asia | J19: 67460 | K19: 50440 | L19: =SUMIFS(Cleaned_Data!$N$4:$N$243,Cleaned_Data!$C$4:$C$243,$H19,Cleaned_Data!$D$4:$D$243,$I19) -> 67197.875 | M19: =SUMIFS(Cleaned_Data!$O$4:$O$243,Cleaned_Data!$C$4:$C$243,$H19,Cleaned_Data!$D$4:$D$243,$I19)+L19*0.18 -> 52081.778
A20: Segment Master | H20: Apr-2025 | I20: South America | J20: 55190 | K20: 38580 | L20: =SUMIFS(Cleaned_Data!$N$4:$N$243,Cleaned_Data!$C$4:$C$243,$H20,Cleaned_Data!$D$4:$D$243,$I20) -> 57175.776 | M20: =SUMIFS(Cleaned_Data!$O$4:$O$243,Cleaned_Data!$C$4:$C$243,$H20,Cleaned_Data!$D$4:$D$243,$I20)+L20*0.18 -> 41491.24
A21: Segment | H21: May-2025 | I21: North America | J21: 73430 | K21: 60580 | L21: =SUMIFS(Cleaned_Data!$N$4:$N$243,Cleaned_Data!$C$4:$C$243,$H21,Cleaned_Data!$D$4:$D$243,$I21) -> 82912.385 | M21: =SUMIFS(Cleaned_Data!$O$4:$O$243,Cleaned_Data!$C$4:$C$243,$H21,Cleaned_Data!$D$4:$D$243,$I21)+L21*0.18 -> 61041.869
A22: Retail | H22: May-2025 | I22: Europe | J22: 57430 | K22: 41550 | L22: =SUMIFS(Cleaned_Data!$N$4:$N$243,Cleaned_Data!$C$4:$C$243,$H22,Cleaned_Data!$D$4:$D$243,$I22) -> 57683.83 | M22: =SUMIFS(Cleaned_Data!$O$4:$O$243,Cleaned_Data!$C$4:$C$243,$H22,Cleaned_Data!$D$4:$D$243,$I22)+L22*0.18 -> 44422.829
A23: Wholesale | H23: May-2025 | I23: Asia | J23: 57950 | K23: 48350 | L23: =SUMIFS(Cleaned_Data!$N$4:$N$243,Cleaned_Data!$C$4:$C$243,$H23,Cleaned_Data!$D$4:$D$243,$I23) -> 62769.471 | M23: =SUMIFS(Cleaned_Data!$O$4:$O$243,Cleaned_Data!$C$4:$C$243,$H23,Cleaned_Data!$D$4:$D$243,$I23)+L23*0.18 -> 47231.735
A24: Online | H24: May-2025 | I24: South America | J24: 41930 | K24: 33530 | L24: =SUMIFS(Cleaned_Data!$N$4:$N$243,Cleaned_Data!$C$4:$C$243,$H24,Cleaned_Data!$D$4:$D$243,$I24) -> 46967.084 | M24: =SUMIFS(Cleaned_Data!$O$4:$O$243,Cleaned_Data!$C$4:$C$243,$H24,Cleaned_Data!$D$4:$D$243,$I24)+L24*0.18 -> 35825.645
H25: Jun-2025 | I25: North America | J25: 80150 | K25: 52310 | L25: =SUMIFS(Cleaned_Data!$N$4:$N$243,Cleaned_Data!$C$4:$C$243,$H25,Cleaned_Data!$D$4:$D$243,$I25) -> 77569.817 | M25: =SUMIFS(Cleaned_Data!$O$4:$O$243,Cleaned_Data!$C$4:$C$243,$H25,Cleaned_Data!$D$4:$D$243,$I25)+L25*0.18 -> 57885.727
H26: Jun-2025 | I26: Europe | J26: 68050 | K26: 51770 | L26: =SUMIFS(Cleaned_Data!$N$4:$N$243,Cleaned_Data!$C$4:$C$243,$H26,Cleaned_Data!$D$4:$D$243,$I26) -> 67381.096 | M26: =SUMIFS(Cleaned_Data!$O$4:$O$243,Cleaned_Data!$C$4:$C$243,$H26,Cleaned_Data!$D$4:$D$243,$I26)+L26*0.18 -> 51387.707
H27: Jun-2025 | I27: Asia | J27: 57090 | K27: 40540 | L27: =SUMIFS(Cleaned_Data!$N$4:$N$243,Cleaned_Data!$C$4:$C$243,$H27,Cleaned_Data!$D$4:$D$243,$I27) -> 56265.852 | M27: =SUMIFS(Cleaned_Data!$O$4:$O$243,Cleaned_Data!$C$4:$C$243,$H27,Cleaned_Data!$D$4:$D$243,$I27)+L27*0.18 -> 41628.633
H28: Jun-2025 | I28: South America | J28: 46700 | K28: 37440 | L28: =SUMIFS(Cleaned_Data!$N$4:$N$243,Cleaned_Data!$C$4:$C$243,$H28,Cleaned_Data!$D$4:$D$243,$I28) -> 49744.052 | M28: =SUMIFS(Cleaned_Data!$O$4:$O$243,Cleaned_Data!$C$4:$C$243,$H28,Cleaned_Data!$D$4:$D$243,$I28)+L28*0.18 -> 39187.339
H29: Jul-2025 | I29: North America | J29: 82290 | K29: 61610 | L29: =SUMIFS(Cleaned_Data!$N$4:$N$243,Cleaned_Data!$C$4:$C$243,$H29,Cleaned_Data!$D$4:$D$243,$I29) -> 77524.273 | M29: =SUMIFS(Cleaned_Data!$O$4:$O$243,Cleaned_Data!$C$4:$C$243,$H29,Cleaned_Data!$D$4:$D$243,$I29)+L29*0.18 -> 60740.169
H30: Jul-2025 | I30: Europe | J30: 65010 | K30: 56280 | L30: =SUMIFS(Cleaned_Data!$N$4:$N$243,Cleaned_Data!$C$4:$C$243,$H30,Cleaned_Data!$D$4:$D$243,$I30) -> 73005.635 | M30: =SUMIFS(Cleaned_Data!$O$4:$O$243,Cleaned_Data!$C$4:$C$243,$H30,Cleaned_Data!$D$4:$D$243,$I30)+L30*0.18 -> 56561.174
H31: Jul-2025 | I31: Asia | J31: 50200 | K31: 41490 | L31: =SUMIFS(Cleaned_Data!$N$4:$N$243,Cleaned_Data!$C$4:$C$243,$H31,Cleaned_Data!$D$4:$D$243,$I31) -> 51765.347 | M31: =SUMIFS(Cleaned_Data!$O$4:$O$243,Cleaned_Data!$C$4:$C$243,$H31,Cleaned_Data!$D$4:$D$243,$I31)+L31*0.18 -> 40588.802
H32: Jul-2025 | I32: South America | J32: 47500 | K32: 38670 | L32: =SUMIFS(Cleaned_Data!$N$4:$N$243,Cleaned_Data!$C$4:$C$243,$H32,Cleaned_Data!$D$4:$D$243,$I32) -> 51454.192 | M32: =SUMIFS(Cleaned_Data!$O$4:$O$243,Cleaned_Data!$C$4:$C$243,$H32,Cleaned_Data!$D$4:$D$243,$I32)+L32*0.18 -> 40746.285
H33: Aug-2025 | I33: North America | J33: 62980 | K33: 55490 | L33: =SUMIFS(Cleaned_Data!$N$4:$N$243,Cleaned_Data!$C$4:$C$243,$H33,Cleaned_Data!$D$4:$D$243,$I33) -> 68478.713 | M33: =SUMIFS(Cleaned_Data!$O$4:$O$243,Cleaned_Data!$C$4:$C$243,$H33,Cleaned_Data!$D$4:$D$243,$I33)+L33*0.18 -> 54305.118
H34: Aug-2025 | I34: Europe | J34: 69370 | K34: 50270 | L34: =SUMIFS(Cleaned_Data!$N$4:$N$243,Cleaned_Data!$C$4:$C$243,$H34,Cleaned_Data!$D$4:$D$243,$I34) -> 70548.018 | M34: =SUMIFS(Cleaned_Data!$O$4:$O$243,Cleaned_Data!$C$4:$C$243,$H34,Cleaned_Data!$D$4:$D$243,$I34)+L34*0.18 -> 53445.533
H35: Aug-2025 | I35: Asia | J35: 68590 | K35: 47150 | L35: =SUMIFS(Cleaned_Data!$N$4:$N$243,Cleaned_Data!$C$4:$C$243,$H35,Cleaned_Data!$D$4:$D$243,$I35) -> 67294.961 | M35: =SUMIFS(Cleaned_Data!$O$4:$O$243,Cleaned_Data!$C$4:$C$243,$H35,Cleaned_Data!$D$4:$D$243,$I35)+L35*0.18 -> 50999.183
H36: Aug-2025 | I36: South America | J36: 52750 | K36: 42680 | L36: =SUMIFS(Cleaned_Data!$N$4:$N$243,Cleaned_Data!$C$4:$C$243,$H36,Cleaned_Data!$D$4:$D$243,$I36) -> 55224.853 | M36: =SUMIFS(Cleaned_Data!$O$4:$O$243,Cleaned_Data!$C$4:$C$243,$H36,Cleaned_Data!$D$4:$D$243,$I36)+L36*0.18 -> 42279.354
... H52: Dec-2025 | I52: South America | J52: 69450 | K52: 48710 | L52: =SUMIFS(Cleaned_Data!$N$4:$N$243,Cleaned_Data!$C$4:$C$243,$H52,Cleaned_Data!$D$4:$D$243,$I52) -> 66661.998 | M52: =SUMIFS(Cleaned_Data!$O$4:$O$243,Cleaned_Data!$C$4:$C$243,$H52,Cleaned_Data!$D$4:$D$243,$I52)+L52*0.18 -> 50402.18

Sheet Advanced_Functions
A1: Advanced Excel Functions — Worked Examples (Part A)
A3: # | B3: Function(s) | C3: Business Question | D3: Formula | E3: Result
A4: 1 | B4: INDEX + MATCH (lookup) | C4: What is Product C's target margin %? | D4: =INDEX(Lookup_Tables!$C$5:$C$9,MATCH("Product C",Lookup_Tables!$A$5:$A$9,0)) | E4: =INDEX(Lookup_Tables!$C$5:$C$9,MATCH("Product C",Lookup_Tables!$A$5:$A$9,0)) -> 0.4
A5: 2 | B5: SUMIFS | C5: Total Net Sales for Asia, Product A | D5: =SUMIFS(Cleaned_Data!$N$4:$N$243,Cleaned_Data!$D$4:$D$243,"Asia",Cleaned_Data!$E$4:$E$243,"Product A") | E5: =SUMIFS(Cleaned_Data!$N$4:$N$243,Cleaned_Data!$D$4:$D$243,"Asia",Cleaned_Data!$E$4:$E$243,"Product A") -> 243564.01
A6: 3 | B6: COUNTIFS | C6: How many transactions were Online segment in Europe? | D6: =COUNTIFS(Cleaned_Data!$D$4:$D$243,"Europe",Cleaned_Data!$G$4:$G$243,"Online") | E6: =COUNTIFS(Cleaned_Data!$D$4:$D$243,"Europe",Cleaned_Data!$G$4:$G$243,"Online") -> 18
A7: 4 | B7: AVERAGEIFS | C7: Average discount % given on Product D orders | D7: =AVERAGEIFS(Cleaned_Data!$K$4:$K$243,Cleaned_Data!$E$4:$E$243,"Product D") | E7: =AVERAGEIFS(Cleaned_Data!$K$4:$K$243,Cleaned_Data!$E$4:$E$243,"Product D") -> 0.061458333
A8: 5 | B8: SUMPRODUCT | C8: Total units sold across all regions and products (cross-check) | D8: =SUMPRODUCT(--(Cleaned_Data!$H$4:$H$243<>""),Cleaned_Data!$H$4:$H$243) | E8: =SUMPRODUCT(--(Cleaned_Data!$H$4:$H$243<>""),Cleaned_Data!$H$4:$H$243) -> 52297
A9: 6 | B9: IFERROR | C9: Safe margin % lookup that returns 0 instead of a divide-by-zero error | D9: =IFERROR(Cleaned_Data!P4/Cleaned_Data!N4,0) | E9: =IFERROR(Cleaned_Data!P4/Cleaned_Data!N4,0) -> 0.38664352
A10: 7 | B10: _xlfn.IFS | C10: Classify row 1's margin as Low/Medium/High | D10: =_xlfn.IFS(Cleaned_Data!Q4<0.2,"Low",Cleaned_Data!Q4<0.4,"Medium",TRUE,"High") | E10: =_xlfn.IFS(Cleaned_Data!Q4<0.2,"Low",Cleaned_Data!Q4<0.4,"Medium",TRUE(),"High") -> Medium
A11: 8 | B11: _xlfn.TEXTJOIN | C11: Build a label from Region + Product for row 1 | D11: =_xlfn.TEXTJOIN(" - ",TRUE,Cleaned_Data!D4,Cleaned_Data!E4) | E11: =_xlfn.TEXTJOIN(" - ",TRUE(),Cleaned_Data!D4,Cleaned_Data!E4) -> North America - Product B
A12: 9 | B12: MAX / INDEX-MATCH combo | C12: Which region had the single highest Net Sales line item? | D12: =INDEX(Cleaned_Data!$D$4:$D$243,MATCH(MAX(Cleaned_Data!$N$4:$N$243),Cleaned_Data!$N$4:$N$243,0)) | E12: =INDEX(Cleaned_Data!$D$4:$D$243,MATCH(MAX(Cleaned_Data!$N$4:$N$243),Cleaned_Data!$N$4:$N$243,0)) -> Europe

Sheet Financial_Model
A1: Financial Model — Monthly Revenue, Profit, Budget Variance & Growth
A3: Month | B3: Total Net Revenue | C3: Total COGS | D3: Gross Profit | E3: Gross Margin % | F3: Budget Revenue | G3: Budget Expense | H3: Revenue Variance $ | I3: Revenue Variance % | J3: MoM Growth %
A4: Jan-2025 | B4: =SUMIFS(Cleaned_Data!$N$4:$N$243,Cleaned_Data!$C$4:$C$243,$A4) -> 245732.03 | C4: =SUMIFS(Cleaned_Data!$O$4:$O$243,Cleaned_Data!$C$4:$C$243,$A4) -> 140649.21 | D4: =B4-C4 -> 105082.82 | E4: =IFERROR(D4/B4,0) -> 0.42763177 | F4: =SUMIFS(Lookup_Tables!$J$5:$J$52,Lookup_Tables!$H$5:$H$52,$A4) -> 248700 | G4: =SUMIFS(Lookup_Tables!$K$5:$K$52,Lookup_Tables!$H$5:$H$52,$A4) -> 175990 | H4: =B4-F4 -> -2967.966 | I4: =IFERROR(H4/F4,0) -> -0.01193392 | J4: =0% -> 0
A5: Feb-2025 | B5: =SUMIFS(Cleaned_Data!$N$4:$N$243,Cleaned_Data!$C$4:$C$243,$A5) -> 255644.91 | C5: =SUMIFS(Cleaned_Data!$O$4:$O$243,Cleaned_Data!$C$4:$C$243,$A5) -> 148826.71 | D5: =B5-C5 -> 106818.2 | E5: =IFERROR(D5/B5,0) -> 0.41783816 | F5: =SUMIFS(Lookup_Tables!$J$5:$J$52,Lookup_Tables!$H$5:$H$52,$A5) -> 250380 | G5: =SUMIFS(Lookup_Tables!$K$5:$K$52,Lookup_Tables!$H$5:$H$52,$A5) -> 190690 | H5: =B5-F5 -> 5264.9075 | I5: =IFERROR(H5/F5,0) -> 0.021027668 | J5: =IFERROR((B5-B4)/B4,0) -> 0.040340176
A6: Mar-2025 | B6: =SUMIFS(Cleaned_Data!$N$4:$N$243,Cleaned_Data!$C$4:$C$243,$A6) -> 258393.81 | C6: =SUMIFS(Cleaned_Data!$O$4:$O$243,Cleaned_Data!$C$4:$C$243,$A6) -> 153544.67 | D6: =B6-C6 -> 104849.14 | E6: =IFERROR(D6/B6,0) -> 0.40577264 | F6: =SUMIFS(Lookup_Tables!$J$5:$J$52,Lookup_Tables!$H$5:$H$52,$A6) -> 261530 | G6: =SUMIFS(Lookup_Tables!$K$5:$K$52,Lookup_Tables!$H$5:$H$52,$A6) -> 193630 | H6: =B6-F6 -> -3136.1925 | I6: =IFERROR(H6/F6,0) -> -0.011991712 | J6: =IFERROR((B6-B5)/B5,0) -> 0.010752806
A7: Apr-2025 | B7: =SUMIFS(Cleaned_Data!$N$4:$N$243,Cleaned_Data!$C$4:$C$243,$A7) -> 282608.57 | C7: =SUMIFS(Cleaned_Data!$O$4:$O$243,Cleaned_Data!$C$4:$C$243,$A7) -> 158672.45 | D7: =B7-C7 -> 123936.12 | E7: =IFERROR(D7/B7,0) -> 0.43854339 | F7: =SUMIFS(Lookup_Tables!$J$5:$J$52,Lookup_Tables!$H$5:$H$52,$A7) -> 264000 | G7: =SUMIFS(Lookup_Tables!$K$5:$K$52,Lookup_Tables!$H$5:$H$52,$A7) -> 200470 | H7: =B7-F7 -> 18608.573 | I7: =IFERROR(H7/F7,0) -> 0.070487019 | J7: =IFERROR((B7-B6)/B6,0) -> 0.093712639
A8: May-2025 | B8: =SUMIFS(Cleaned_Data!$N$4:$N$243,Cleaned_Data!$C$4:$C$243,$A8) -> 250332.77 | C8: =SUMIFS(Cleaned_Data!$O$4:$O$243,Cleaned_Data!$C$4:$C$243,$A8) -> 143462.18 | D8: =B8-C8 -> 106870.59 | E8: =IFERROR(D8/B8,0) -> 0.4269141 | F8: =SUMIFS(Lookup_Tables!$J$5:$J$52,Lookup_Tables!$H$5:$H$52,$A8) -> 230740 | G8: =SUMIFS(Lookup_Tables!$K$5:$K$52,Lookup_Tables!$H$5:$H$52,$A8) -> 184010 | H8: =B8-F8 -> 19592.77 | I8: =IFERROR(H8/F8,0) -> 0.084912761 | J8: =IFERROR((B8-B7)/B7,0) -> -0.11420674
A9: Jun-2025 | B9: =SUMIFS(Cleaned_Data!$N$4:$N$243,Cleaned_Data!$C$4:$C$243,$A9) -> 250960.82 | C9: =SUMIFS(Cleaned_Data!$O$4:$O$243,Cleaned_Data!$C$4:$C$243,$A9) -> 144916.46 | D9: =B9-C9 -> 106044.36 | E9: =IFERROR(D9/B9,0) -> 0.42255344 | F9: =SUMIFS(Lookup_Tables!$J$5:$J$52,Lookup_Tables!$H$5:$H$52,$A9) -> 251990 | G9: =SUMIFS(Lookup_Tables!$K$5:$K$52,Lookup_Tables!$H$5:$H$52,$A9) -> 182060 | H9: =B9-F9 -> -1029.1825 | I9: =IFERROR(H9/F9,0) -> -0.0040842196 | J9: =IFERROR((B9-B8)/B8,0) -> 0.0025088485
A10: Jul-2025 | B10: =SUMIFS(Cleaned_Data!$N$4:$N$243,Cleaned_Data!$C$4:$C$243,$A10) -> 253749.45 | C10: =SUMIFS(Cleaned_Data!$O$4:$O$243,Cleaned_Data!$C$4:$C$243,$A10) -> 152961.53 | D10: =B10-C10 -> 100787.92 | E10: =IFERROR(D10/B10,0) -> 0.39719463 | F10: =SUMIFS(Lookup_Tables!$J$5:$J$52,Lookup_Tables!$H$5:$H$52,$A10) -> 245000 | G10: =SUMIFS(Lookup_Tables!$K$5:$K$52,Lookup_Tables!$H$5:$H$52,$A10) -> 198050 | H10: =B10-F10 -> 8749.4465 | I10: =IFERROR(H10/F10,0) -> 0.035712027 | J10: =IFERROR((B10-B9)/B9,0) -> 0.01111181
A11: Aug-2025 | B11: =SUMIFS(Cleaned_Data!$N$4:$N$243,Cleaned_Data!$C$4:$C$243,$A11) -> 261546.54 | C11: =SUMIFS(Cleaned_Data!$O$4:$O$243,Cleaned_Data!$C$4:$C$243,$A11) -> 153950.81 | D11: =B11-C11 -> 107595.73 | E11: =IFERROR(D11/B11,0) -> 0.41138274 | F11: =SUMIFS(Lookup_Tables!$J$5:$J$52,Lookup_Tables!$H$5:$H$52,$A11) -> 253690 | G11: =SUMIFS(Lookup_Tables!$K$5:$K$52,Lookup_Tables!$H$5:$H$52,$A11) -> 195590 | H11: =B11-F11 -> 7856.5445 | I11: =IFERROR(H11/F11,0) -> 0.030969074 | J11: =IFERROR((B11-B10)/B10,0) -> 0.030727547
A12: Sep-2025 | B12: =SUMIFS(Cleaned_Data!$N$4:$N$243,Cleaned_Data!$C$4:$C$243,$A12) -> 261949.24 | C12: =SUMIFS(Cleaned_Data!$O$4:$O$243,Cleaned_Data!$C$4:$C$243,$A12) -> 152967.95 | D12: =B12-C12 -> 108981.29 | E12: =IFERROR(D12/B12,0) -> 0.41603972 | F12: =SUMIFS(Lookup_Tables!$J$5:$J$52,Lookup_Tables!$H$5:$H$52,$A12) -> 247420 | G12: =SUMIFS(Lookup_Tables!$K$5:$K$52,Lookup_Tables!$H$5:$H$52,$A12) -> 195930 | H12: =B12-F12 -> 14529.237 | I12: =IFERROR(H12/F12,0) -> 0.058722967 | J12: =IFERROR((B12-B11)/B11,0) -> 0.0015396571
A13: Oct-2025 | B13: =SUMIFS(Cleaned_Data!$N$4:$N$243,Cleaned_Data!$C$4:$C$243,$A13) -> 289560.52 | C13: =SUMIFS(Cleaned_Data!$O$4:$O$243,Cleaned_Data!$C$4:$C$243,$A13) -> 166367.88 | D13: =B13-C13 -> 123192.64 | E13: =IFERROR(D13/B13,0) -> 0.42544696 | F13: =SUMIFS(Lookup_Tables!$J$5:$J$52,Lookup_Tables!$H$5:$H$52,$A13) -> 276440 | G13: =SUMIFS(Lookup_Tables!$K$5:$K$52,Lookup_Tables!$H$5:$H$52,$A13) -> 207350 | H13: =B13-F13 -> 13120.524 | I13: =IFERROR(H13/F13,0) -> 0.047462467 | J13: =IFERROR((B13-B12)/B12,0) -> 0.10540702
A14: Nov-2025 | B14: =SUMIFS(Cleaned_Data!$N$4:$N$243,Cleaned_Data!$C$4:$C$243,$A14) -> 332865.62 | C14: =SUMIFS(Cleaned_Data!$O$4:$O$243,Cleaned_Data!$C$4:$C$243,$A14) -> 195068.36 | D14: =B14-C14 -> 137797.26 | E14: =IFERROR(D14/B14,0) -> 0.41397264 | F14: =SUMIFS(Lookup_Tables!$J$5:$J$52,Lookup_Tables!$H$5:$H$52,$A14) -> 329750 | G14: =SUMIFS(Lookup_Tables!$K$5:$K$52,Lookup_Tables!$H$5:$H$52,$A14) -> 250450 | H14: =B14-F14 -> 3115.621 | I14: =IFERROR(H14/F14,0) -> 0.0094484337 | J14: =IFERROR((B14-B13)/B13,0) -> 0.14955456
A15: Dec-2025 | B15: =SUMIFS(Cleaned_Data!$N$4:$N$243,Cleaned_Data!$C$4:$C$243,$A15) -> 330908.47 | C15: =SUMIFS(Cleaned_Data!$O$4:$O$243,Cleaned_Data!$C$4:$C$243,$A15) -> 190644.87 | D15: =B15-C15 -> 140263.6 | E15: =IFERROR(D15/B15,0) -> 0.42387431 | F15: =SUMIFS(Lookup_Tables!$J$5:$J$52,Lookup_Tables!$H$5:$H$52,$A15) -> 332020 | G15: =SUMIFS(Lookup_Tables!$K$5:$K$52,Lookup_Tables!$H$5:$H$52,$A15) -> 239340 | H15: =B15-F15 -> -1111.5325 | I15: =IFERROR(H15/F15,0) -> -0.0033477878 | J15: =IFERROR((B15-B14)/B14,0) -> -0.0058797105
A16: FY 2025 Total | B16: =SUM(B4:B15) -> 3274252.8 | C16: =SUM(C4:C15) -> 1902033.1 | D16: =SUM(D4:D15) -> 1372219.7 | E16: =IFERROR(D16/B16,0) -> 0.419094 | F16: =SUM(F4:F15) -> 3191660 | G16: =SUM(G4:G15) -> 2413560 | H16: =SUM(H4:H15) -> 82592.75 | I16: =IFERROR(H16/F16,0) -> 0.025877678
A19: Regional Performance (FY2025)
A20: Region | B20: Net Revenue | C20: Gross Profit | D20: Margin %
A21: North America | B21: =SUMIFS(Cleaned_Data!$N$4:$N$243,Cleaned_Data!$D$4:$D$243,$A21) -> 936068.77 | C21: =SUMIFS(Cleaned_Data!$P$4:$P$243,Cleaned_Data!$D$4:$D$243,$A21) -> 391571.88 | D21: =IFERROR(C21/B21,0) -> 0.41831529
A22: Europe | B22: =SUMIFS(Cleaned_Data!$N$4:$N$243,Cleaned_Data!$D$4:$D$243,$A22) -> 890871.39 | C22: =SUMIFS(Cleaned_Data!$P$4:$P$243,Cleaned_Data!$D$4:$D$243,$A22) -> 374395.72 | D22: =IFERROR(C22/B22,0) -> 0.42025788
A23: Asia | B23: =SUMIFS(Cleaned_Data!$N$4:$N$243,Cleaned_Data!$D$4:$D$243,$A23) -> 761503.63 | C23: =SUMIFS(Cleaned_Data!$P$4:$P$243,Cleaned_Data!$D$4:$D$243,$A23) -> 315470.75 | D23: =IFERROR(C23/B23,0) -> 0.41427347
A24: South America | B24: =SUMIFS(Cleaned_Data!$N$4:$N$243,Cleaned_Data!$D$4:$D$243,$A24) -> 685808.96 | C24: =SUMIFS(Cleaned_Data!$P$4:$P$243,Cleaned_Data!$D$4:$D$243,$A24) -> 290781.32 | D24: =IFERROR(C24/B24,0) -> 0.42399755
A26: Product Performance (FY2025)
A27: Product | B27: Category | C27: Net Revenue | D27: Gross Profit | E27: Margin %
A28: Product A | B28: Electronics | C28: =SUMIFS(Cleaned_Data!$N$4:$N$243,Cleaned_Data!$E$4:$E$243,$A28) -> 1094651.1 | D28: =SUMIFS(Cleaned_Data!$P$4:$P$243,Cleaned_Data!$E$4:$E$243,$A28) -> 408258.32 | E28: =IFERROR(D28/C28,0) -> 0.37295749
A29: Product B | B29: Electronics | C29: =SUMIFS(Cleaned_Data!$N$4:$N$243,Cleaned_Data!$E$4:$E$243,$A29) -> 830917.8 | D29: =SUMIFS(Cleaned_Data!$P$4:$P$243,Cleaned_Data!$E$4:$E$243,$A29) -> 303447.89 | E29: =IFERROR(D29/C29,0) -> 0.36519604
A30: Product C | B30: Home & Living | C30: =SUMIFS(Cleaned_Data!$N$4:$N$243,Cleaned_Data!$E$4:$E$243,$A30) -> 445169.29 | D30: =SUMIFS(Cleaned_Data!$P$4:$P$243,Cleaned_Data!$E$4:$E$243,$A30) -> 206914.39 | E30: =IFERROR(D30/C30,0) -> 0.46479933
A31: Product D | B31: Apparel | C31: =SUMIFS(Cleaned_Data!$N$4:$N$243,Cleaned_Data!$E$4:$E$243,$A31) -> 291080.24 | D31: =SUMIFS(Cleaned_Data!$P$4:$P$243,Cleaned_Data!$E$4:$E$243,$A31) -> 145960.03 | E31: =IFERROR(D31/C31,0) -> 0.50144259
A32: Product E | B32: Apparel | C32: =SUMIFS(Cleaned_Data!$N$4:$N$243,Cleaned_Data!$E$4:$E$243,$A32) -> 612434.32 | D32: =SUMIFS(Cleaned_Data!$P$4:$P$243,Cleaned_Data!$E$4:$E$243,$A32) -> 307639.04 | E32: =IFERROR(D32/C32,0) -> 0.50232168

Sheet Forecast
A1: Revenue Forecast — 3-Month Moving Average & Linear Trend (Q1 2026)
A3: What-If growth adjustment (applied to trend forecast): | E3: 0 | I3: Trend slope | J3: =SLOPE($B$6:$B$17,$G$6:$G$17) -> 6235.0611
I4: Trend intercept | J4: =INTERCEPT($B$6:$B$17,$G$6:$G$17) -> 232326.5
A5: Month | B5: Actual Revenue | C5: 3-Mo Moving Avg | D5: Linear Trend Forecast | E5: Trend + What-If
A6: Jan-2025 | B6: =Financial_Model!B4 -> 245732.03 | D6: =$J$3*G6+$J$4 -> 238561.56 | E6: =D6*(1+$E$3) -> 238561.56 | G6: 1
A7: Feb-2025 | B7: =Financial_Model!B5 -> 255644.91 | D7: =$J$3*G7+$J$4 -> 244796.62 | E7: =D7*(1+$E$3) -> 244796.62 | G7: 2
A8: Mar-2025 | B8: =Financial_Model!B6 -> 258393.81 | C8: =AVERAGE(B6:B8) -> 253256.92 | D8: =$J$3*G8+$J$4 -> 251031.68 | E8: =D8*(1+$E$3) -> 251031.68 | G8: 3
A9: Apr-2025 | B9: =Financial_Model!B7 -> 282608.57 | C9: =AVERAGE(B7:B9) -> 265549.1 | D9: =$J$3*G9+$J$4 -> 257266.74 | E9: =D9*(1+$E$3) -> 257266.74 | G9: 4
A10: May-2025 | B10: =Financial_Model!B8 -> 250332.77 | C10: =AVERAGE(B8:B10) -> 263778.38 | D10: =$J$3*G10+$J$4 -> 263501.8 | E10: =D10*(1+$E$3) -> 263501.8 | G10: 5
A11: Jun-2025 | B11: =Financial_Model!B9 -> 250960.82 | C11: =AVERAGE(B9:B11) -> 261300.72 | D11: =$J$3*G11+$J$4 -> 269736.87 | E11: =D11*(1+$E$3) -> 269736.87 | G11: 6
A12: Jul-2025 | B12: =Financial_Model!B10 -> 253749.45 | C12: =AVERAGE(B10:B12) -> 251681.01 | D12: =$J$3*G12+$J$4 -> 275971.93 | E12: =D12*(1+$E$3) -> 275971.93 | G12: 7
A13: Aug-2025 | B13: =Financial_Model!B11 -> 261546.54 | C13: =AVERAGE(B11:B13) -> 255418.94 | D13: =$J$3*G13+$J$4 -> 282206.99 | E13: =D13*(1+$E$3) -> 282206.99 | G13: 8
A14: Sep-2025 | B14: =Financial_Model!B12 -> 261949.24 | C14: =AVERAGE(B12:B14) -> 259081.74 | D14: =$J$3*G14+$J$4 -> 288442.05 | E14: =D14*(1+$E$3) -> 288442.05 | G14: 9
A15: Oct-2025 | B15: =Financial_Model!B13 -> 289560.52 | C15: =AVERAGE(B13:B15) -> 271018.77 | D15: =$J$3*G15+$J$4 -> 294677.11 | E15: =D15*(1+$E$3) -> 294677.11 | G15: 10
A16: Nov-2025 | B16: =Financial_Model!B14 -> 332865.62 | C16: =AVERAGE(B14:B16) -> 294791.79 | D16: =$J$3*G16+$J$4 -> 300912.17 | E16: =D16*(1+$E$3) -> 300912.17 | G16: 11
A17: Dec-2025 | B17: =Financial_Model!B15 -> 330908.47 | C17: =AVERAGE(B15:B17) -> 317778.2 | D17: =$J$3*G17+$J$4 -> 307147.23 | E17: =D17*(1+$E$3) -> 307147.23 | G17: 12
A19: Forecast — Next 3 Months (Q1 2026)
A20: Month | B20: Trend Forecast | C20: Trend + What-If
A21: Jan-2026 | B21: =$J$3*13+$J$4 -> 313382.29 | C21: =B21*(1+$E$3) -> 313382.29
A22: Feb-2026 | B22: =$J$3*14+$J$4 -> 319617.35 | C22: =B22*(1+$E$3) -> 319617.35
A23: Mar-2026 | B23: =$J$3*15+$J$4 -> 325852.42 | C23: =B23*(1+$E$3) -> 325852.42

Sheet Dashboard
B1: Enterprise Sales Performance & Financial Analytics Dashboard
B2: FY 2025 — All Regions
B4: Total Net Revenue | E4: Total Gross Profit | H4: Avg Gross Margin % | K4: Revenue vs Budget
B5: =Financial_Model!B16 -> 3274252.8 | E5: =Financial_Model!D16 -> 1372219.7 | H5: =Financial_Model!E16 -> 0.419094 | K5: =Financial_Model!I16 -> 0.025877678
B9: Monthly Revenue Trend — Actual vs Budget

Sheet Executive_Summary
B2: Executive Summary — Business Insights
B3: Enterprise Sales Performance & Financial Analytics Dashboard, FY2025
B5: 1. Which products generate the highest profit?
B6: =INDEX(Financial_Model!$A$28:$A$32,MATCH(MAX(Financial_Model!$D$28:$D$32),Financial_Model!$D$28:$D$32,0))&" leads on gross profit; see Financial_Model Product Performance table for the full ranking." -> Product A leads on gross profit; see Financial_Model Product Performance table for the full ranking.
B8: 2. Which region has the strongest growth?
B9: =INDEX(Financial_Model!$A$21:$A$24,MATCH(MAX(Financial_Model!$B$21:$B$24),Financial_Model!$B$21:$B$24,0))&" leads on total net revenue for FY2025; check the Dashboard region chart for the month-by-month pattern." -> North America leads on total net revenue for FY2025; check the Dashboard region chart for the month-by-month pattern.
B11: 3. What are the major business risks?
B12: ="Revenue vs Budget variance is "&TEXT(Financial_Model!I16,"0.0%")&" for the year — months running below budget (see the Financial_Model Revenue Variance % column) are the ones to review first; discounting above 10% on lower-margin products is the other watch item." -> Revenue vs Budget variance is 2.6% for the year — months running below budget (see the Financial_Model Revenue Variance % column) are the ones to review first; discounting above 10% on lower-margin products is the other watch item.
B14: 4. What forecasting insights support strategic planning?
B15: ="The linear trend model projects Q1 2026 monthly revenue near "&TEXT(Forecast!B21,"$#,##0")&" to "&TEXT(Forecast!B23,"$#,##0")&"; use the Forecast sheet What-If cell to stress-test more optimistic or conservative growth assumptions." -> The linear trend model projects Q1 2026 monthly revenue near $313,382 to $325,852; use the Forecast sheet What-If cell to stress-test more optimistic or conservative growth assumptions.
B18: Recommendations
B20: • Reallocate marketing spend toward the top-performing region and product pair identified above.
B21: • Investigate months where Revenue Variance % is negative in Financial_Model before the Q1 2026 budget is locked.
B22: • Standardize the discount policy — Advanced_Functions row 4 shows average discounting by product for a starting benchmark.
B23: • Re-run the Forecast sheet's What-If cell against the FY2026 budget target once it's set.
